natsu/__init__.py
natsu/natsu.py
natsu-1.0.1.dist-info/LICENSE.md
natsu-1.0.1.dist-info/WHEEL
natsu-1.0.1.dist-info/METADATA
natsu-1.0.1.dist-info/RECORD
